Metadata-Version: 2.1
Name: posteriorstacker
Version: 0.6.2
Summary: Combine Bayesian analyses from many datasets. Easy sample parameter distributions.
Home-page: https://github.com/JohannesBuchner/PosteriorStacker
Author: Johannes Buchner
Author-email: johannes.buchner.acad@gmx.com
License: GNU General Public License v3
Keywords: posteriorstacker
Classifier: Development Status :: 2 - Pre-Alpha
Classifier: Intended Audience :: Developers
Classifier: License :: OSI Approved :: GNU General Public License v3 (GPLv3)
Classifier: Natural Language :: English
Classifier: Programming Language :: Python :: 3.5
Classifier: Programming Language :: Python :: 3.6
Classifier: Programming Language :: Python :: 3.7
Classifier: Programming Language :: Python :: 3.8
Classifier: Programming Language :: Python :: 3.9
Requires-Python: >= 3.5
License-File: LICENSE
License-File: COPYING
Requires-Dist: numpy
Requires-Dist: scipy
Requires-Dist: ultranest
Requires-Dist: matplotlib
Requires-Dist: pandas
